{
    "_id": "LRGASP:LRGASP_challenge-1_human_NIC_CapTrap-ONT-LS", 
    "challenge_ids": [
        "human_NIC_CapTrap-ONT-LS"
    ], 
    "datalink": {
        "inline_data": {
            "challenge_participants": [
                {
                    "metric_y": 24.22, 
                    "participant_id": "TALON_LAPA"
                }
            ], 
            "visualization": {
                "type": "bar-plot", 
                "y_axis": "intron_retention_incidence_%"
            }
        }
    }, 
    "type": "aggregation"
}