{
    "_id": "LRGASP:LRGASP_challenge-1_human_ISM_R2C2-ONT-LO", 
    "challenge_ids": [
        "human_ISM_R2C2-ONT-LO"
    ], 
    "datalink": {
        "inline_data": {
            "challenge_participants": [
                {
                    "metric_y": 88.2, 
                    "metric_x": 77.58, 
                    "participant_id": "LyRic"
                }, 
                {
                    "metric_y": 71.64, 
                    "metric_x": 75.57, 
                    "participant_id": "Mandalorion"
                }, 
                {
                    "metric_y": 80.41, 
                    "metric_x": 59.11, 
                    "participant_id": "IsoQuant"
                }, 
                {
                    "metric_y": 89.82, 
                    "metric_x": 48.32, 
                    "participant_id": "TALON_LAPA"
                }, 
                {
                    "metric_y": 88.05, 
                    "metric_x": 68.69, 
                    "participant_id": "Bambu"
                }
            ], 
            "visualization": {
                "type": "2D-plot", 
                "y_axis": "3_polya_supported_%", 
                "x_axis": "5_cage_supported_%"
            }
        }
    }, 
    "type": "aggregation"
}