{
    "_id": "LRGASP:LRGASP_challenge-1_human_FSM_CapTrap-PacBio-LO", 
    "challenge_ids": [
        "human_FSM_CapTrap-PacBio-LO"
    ], 
    "datalink": {
        "inline_data": {
            "challenge_participants": [
                {
                    "metric_y": 98.89, 
                    "participant_id": "LyRic"
                }, 
                {
                    "metric_y": 81.89, 
                    "participant_id": "Bambu"
                }, 
                {
                    "metric_y": 97.31, 
                    "participant_id": "FLAMES"
                }, 
                {
                    "metric_y": 85.23, 
                    "participant_id": "IsoQuant"
                }, 
                {
                    "metric_y": 95.03, 
                    "participant_id": "TALON_LAPA"
                }
            ], 
            "visualization": {
                "type": "bar-plot", 
                "y_axis": "3_polya_supported_%"
            }
        }
    }, 
    "type": "aggregation"
}